{
  "title": "Fortune Movie",
  "group_id": "hasunosora",
  "url": "https://love-live.fandom.com/wiki/Fortune_Movie",
  "artist": [
    "Cerise Bouquet"
  ],
  "album": "",
  "released": "April 26, 2023",
  "composer": [
    "Arisa Momou",
    "Menma"
  ],
  "arranger": [
    "Menma"
  ],
  "lyricist": [],
  "center": "Kaho Hinoshita",
  "spotify": "https://open.spotify.com/track/14Psf2FqhXX29QRDrsVoLG",
  "duration": "",
  "categories": [
    "Cerise Bouquet",
    "Lyrics",
    "Discography:Hasunosora",
    "Link! Like! Love Live!"
  ],
  "description": "is the second song included in Cerise Bouquet's first single. It was released on April 26, 2023.",
  "infobox": {
    "Artist": "Cerise Bouquet",
    "Center": "Kaho Hinoshita",
    "Released": "April 26, 2023",
    "Format": "CD",
    "Recorded": "2023",
    "Label": "Lantis",
    "Documented Reference": "",
    "Image": "<gallery>",
    "Menma]], and arranged by Menma.": "=SIF 2: Miracle Live Description==",
    "Preview": "[[File:【PREVIEW】 Cerise Bouquet 1st Single \"Reflection in the mirror\""
  },
  "lyrics": {
    "english": "/lyrics/hasunosora/fortune-movie/english.txt",
    "romaji": "/lyrics/hasunosora/fortune-movie/romaji.txt",
    "kanji": "/lyrics/hasunosora/fortune-movie/kanji.txt"
  }
}