{
  "title": "Happy Shijou Shugi!",
  "group_id": "hasunosora",
  "url": "https://love-live.fandom.com/wiki/Happy_Shijou_Shugi!",
  "artist": [
    "KahoMegu♡Gelato"
  ],
  "album": "",
  "released": "March 20, 2024",
  "composer": [
    "Takayuki Tomokiyo"
  ],
  "arranger": [
    "EFFY"
  ],
  "lyricist": [],
  "center": "Megumi Fujishima",
  "spotify": "https://open.spotify.com/track/1sAZfB4irnhGYbbyS31WaI",
  "duration": "",
  "categories": [
    "Kaho Hinoshita",
    "Megumi Fujishima",
    "Lyrics",
    "Discography:Hasunosora",
    "Link! Like! Love Live!"
  ],
  "description": "is a song sung by , a shuffle unit consisting of Kaho Hinoshita and Megumi Fujishima. It was released on March 20, 2024.",
  "infobox": {
    "Artist": "KahoMegu♡Gelato",
    "Center": "Megumi Fujishima",
    "Released": "March 20, 2024",
    "Format": "CD",
    "Recorded": "2024",
    "Label": "Lantis",
    "Documented Reference": "",
    "Image": "<gallery>",
    "EFFY]].": "=Track Listing=="
  },
  "lyrics": {
    "english": "/lyrics/hasunosora/happy-shijou-shugi/english.txt",
    "romaji": "/lyrics/hasunosora/happy-shijou-shugi/romaji.txt",
    "kanji": "/lyrics/hasunosora/happy-shijou-shugi/kanji.txt"
  }
}