{
  "title": "Thank you Good morning",
  "group_id": "liella",
  "url": "https://love-live.fandom.com/wiki/Thank_you_Good_morning",
  "artist": [
    "5yncri5e!"
  ],
  "album": "",
  "released": "April 24, 2024",
  "composer": [
    "Yuki Utamaru"
  ],
  "arranger": [
    "Gou Ishikuro"
  ],
  "lyricist": [
    "Junko Miyajima"
  ],
  "center": "",
  "spotify": "https://open.spotify.com/track/4v32xB13Zhm3OrOlNgjjUz",
  "duration": "",
  "categories": [
    "Discography:Liella!",
    "Love Live! Superstar!!",
    "Sub-unit Songs:Liella!",
    "5yncri5e!",
    "Lyrics",
    "Chisato Arashi",
    "Kinako Sakurakoji",
    "Shiki Wakana",
    "Natsumi Onitsuka",
    "Tomari Onitsuka",
    "Liella! Songs"
  ],
  "description": "Thank you Good morning is a song from the first single sung by 5yncri5e!. It was released on April 24, 2024.",
  "infobox": {
    "Image": "5yncri5e! Jellyfish.jpg",
    "Artist": "5yncri5e!",
    "Released": "April 24, 2024",
    "Recorded": "2024",
    "Label": "Lantis"
  },
  "lyrics": {
    "english": "/lyrics/liella/thank-you-good-morning/english.txt",
    "romaji": "/lyrics/liella/thank-you-good-morning/romaji.txt",
    "kanji": "/lyrics/liella/thank-you-good-morning/kanji.txt"
  }
}