{
  "title": "Concentrate!",
  "group_id": "nijigasaki",
  "url": "https://love-live.fandom.com/wiki/Concentrate!",
  "artist": [
    "Nijigasaki High School Idol Club"
  ],
  "album": "",
  "released": "October 13, 2021",
  "composer": [],
  "arranger": [
    "soranoalto"
  ],
  "lyricist": [
    "Mikio Muraki"
  ],
  "center": "",
  "spotify": "https://open.spotify.com/track/0v10SSlwvEUCPYsgjEBBFR",
  "duration": "",
  "categories": [
    "Discography:Nijigaku",
    "Shioriko Mifune",
    "Lyrics",
    "Love Live! Nijigaku"
  ],
  "description": "Concentrate! (コンセントレイト！) is a song sung by Shioriko Mifune that appears on Nijigasaki High School Idol Club's 4th album. It was released on October 13, 2021.",
  "infobox": {
    "Artist": "Nijigasaki High School Idol Club",
    "Center": "",
    "Released": "October 13, 2021",
    "Format": "",
    "Recorded": "2021",
    "Genre": "Anime",
    "Length": "",
    "Label": "Lantis",
    "Image": "L! L! L! Love the Life We Live.jpg",
    "soranoalto]].": "= SIF 2: Miracle Live Description ==",
    "lit. Night-luminous Pearl}}": "=Video=="
  },
  "lyrics": {
    "english": "/lyrics/nijigasaki/concentrate/english.txt",
    "romaji": "/lyrics/nijigasaki/concentrate/romaji.txt",
    "kanji": "/lyrics/nijigasaki/concentrate/kanji.txt"
  }
}