{
  "title": "Ketsui no Hikari",
  "group_id": "nijigasaki",
  "url": "https://love-live.fandom.com/wiki/Ketsui_no_Hikari",
  "artist": [
    "Nijigasaki High School Idol Club"
  ],
  "album": "",
  "released": "September 2, 2020",
  "composer": [],
  "arranger": [
    "Ayumu Nakamura",
    "Hiroto Kikuchi"
  ],
  "lyricist": [],
  "center": "",
  "spotify": "https://open.spotify.com/track/5bKOT6xcTF9SLJw4sKgb2s",
  "duration": "",
  "categories": [
    "Discography:Nijigaku",
    "Shioriko Mifune",
    "Lyrics",
    "Love Live! Nijigaku"
  ],
  "description": "is the tenth song on Nijigasaki High School Idol Club's 3rd album. It is sung by Shioriko Mifune. It was added to Love Live! School Idol Festival ALL STARS as a surprise release in commemoration of her being added into the game.",
  "infobox": {
    "Image": "Just Believe!!!.jpg",
    "Artist": "Nijigasaki High School Idol Club",
    "Center": "",
    "Released": "September 2, 2020",
    "Format": "",
    "Recorded": "2020",
    "Genre": "",
    "Length": "",
    "Label": "Lantis",
    "Hiroto Kikuchi]].": "= SIF 2: Miracle Live Description =="
  },
  "lyrics": {
    "english": "/lyrics/nijigasaki/ketsui-no-hikari/english.txt",
    "romaji": "/lyrics/nijigasaki/ketsui-no-hikari/romaji.txt",
    "kanji": "/lyrics/nijigasaki/ketsui-no-hikari/kanji.txt"
  }
}