{
  "title": "Sangoshou no Kioku",
  "group_id": "nijigasaki",
  "url": "https://love-live.fandom.com/wiki/Sangoshou_no_Kioku",
  "artist": [
    "Naoki Endo",
    "Nijigasaki High School Idol Club"
  ],
  "album": "",
  "released": "December 4, 2024",
  "composer": [],
  "arranger": [],
  "lyricist": [],
  "center": "",
  "spotify": "",
  "duration": "",
  "categories": [
    "Discography:Nijigaku",
    "Original Soundtracks",
    "Love Live! Nijigaku"
  ],
  "description": "is an album containing BGM tracks and insert songs from the first part of the Nijigasaki High School Idol Club movie triology. It also contains partial solo versions of Doko ni Itemo Kimi wa Kimi.",
  "infobox": {
    "Image": "Nijigasaki The Movie Final Chapter Part 1 OST Sangoshou no Kioku.jpg",
    "Artist": "Naoki Endo & Nijigasaki High School Idol Club",
    "Released": "December 4, 2024",
    "Format": "CD",
    "Recorded": "2024",
    "Label": "Lantis",
    "Previous": "Bound for TOKIMEKI",
    "Next": "Sazameki no Machikado"
  },
  "lyrics": {
    "english": null,
    "romaji": null,
    "kanji": null
  }
}