{
  "title": "SOL de ROSA",
  "group_id": "nijigasaki",
  "url": "https://love-live.fandom.com/wiki/SOL_de_ROSA",
  "artist": [
    "Ai Miyashita",
    "Lanzhu Zhong"
  ],
  "album": "",
  "released": "December 17, 2025",
  "composer": [],
  "arranger": [
    "Aiobahn +81"
  ],
  "lyricist": [
    "Ayaka Miyake"
  ],
  "center": "",
  "spotify": "https://open.spotify.com/track/1IfYaoHnzwscnNAP2IThSG",
  "duration": "",
  "categories": [
    "Discography:Nijigaku",
    "Lyrics",
    "Love Live! Nijigaku",
    "Ai Miyashita",
    "Lanzhu Zhong",
    "Duo Trio Songs"
  ],
  "description": "SOL de ROSA is a song included in NIJIGAKU FLOWER MUSIC which was released on December 17, 2025. It is sung by Ai Miyashita and Lanzhu Zhong.",
  "infobox": {
    "Image": "NIJIGAKU FLOWER MUSIC -Ai Miyashita & Lanzhu Zhong Edition-.jpg",
    "Artist": "Ai Miyashita & Lanzhu Zhong",
    "Center": "",
    "Released": "December 17, 2025",
    "Format": "CD",
    "Recorded": "2025",
    "Genre": "Anime",
    "Length": "",
    "Label": "Lantis",
    "Aiobahn +81]].": "=Tracklist==",
    "Preview": "[[File:【PREVIEW】NIJIGAKU FLOWER MUSIC"
  },
  "lyrics": {
    "english": null,
    "romaji": "/lyrics/nijigasaki/sol-de-rosa/romaji.txt",
    "kanji": "/lyrics/nijigasaki/sol-de-rosa/kanji.txt"
  }
}