{
  "title": "Tanoshii no Tensai",
  "group_id": "nijigasaki",
  "url": "https://love-live.fandom.com/wiki/Tanoshii_no_Tensai",
  "artist": [
    "Nijigasaki High School Idol Club"
  ],
  "album": "",
  "released": "September 2, 2020",
  "composer": [
    "Akira Sunset",
    "[[Composers",
    "Arrangers|Carlos K"
  ],
  "arranger": [
    "Carlos K"
  ],
  "lyricist": [
    "Akira Sunset"
  ],
  "center": "",
  "spotify": "https://open.spotify.com/track/6BR9SPM7tKuD7wGOkx4CYd",
  "duration": "",
  "categories": [
    "Discography:Nijigaku",
    "Ai Miyashita",
    "Lyrics",
    "Love Live! Nijigaku"
  ],
  "description": "is the fifth song on Nijigasaki High School Idol Club's 3rd album. It is sung by Ai Miyashita.",
  "infobox": {
    "Artist": "Nijigasaki High School Idol Club",
    "Center": "",
    "Released": "September 2, 2020",
    "Format": "",
    "Recorded": "2020",
    "Genre": "Anime",
    "Length": "",
    "Label": "Lantis",
    "Image": "Just Believe!!!.jpg",
    "Carlos K.]], arranged by Carlos K.": "= SIF 2: Miracle Live Description =="
  },
  "lyrics": {
    "english": "/lyrics/nijigasaki/tanoshii-no-tensai/english.txt",
    "romaji": "/lyrics/nijigasaki/tanoshii-no-tensai/romaji.txt",
    "kanji": "/lyrics/nijigasaki/tanoshii-no-tensai/kanji.txt"
  }
}