{
  "title": "Wawawa☆What's up!",
  "group_id": "nijigasaki",
  "url": "https://love-live.fandom.com/wiki/Wawawa☆What's_up!",
  "artist": [
    "Nijigasaki High School Idol Club"
  ],
  "album": "",
  "released": "July 5, 2023",
  "composer": [],
  "arranger": [
    "Keisuke Koyama"
  ],
  "lyricist": [
    "miyakei"
  ],
  "center": "",
  "spotify": "https://open.spotify.com/track/33DWpvGvA4dblsl0zZbtF4",
  "duration": "",
  "categories": [
    "Discography:Nijigaku",
    "Love Live! Nijigaku",
    "Unit Songs:Nijigaku",
    "Nijigaku Insert Songs",
    "Animated Songs:Nijigaku",
    "Lyrics"
  ],
  "description": "Wawawa☆What's up! is Nijigasaki High School Idol Club's song for the single that was released on July 5, 2023. It plays during the credits for the Love Live! Nijigasaki High School Idol Club OVA.",
  "infobox": {
    "Artist": "Nijigasaki High School Idol Club",
    "Released": "July 5, 2023",
    "Format": "CD",
    "Recorded": "2023",
    "Genre": "Anime",
    "Length": "",
    "Label": "Lantis",
    "Image": "Nijigasaki SINGING, DREAMING, NOW!.jpg",
    "Keisuke Koyama]].": "=SIF 2: Miracle Live Description==",
    "NEXT SKY]], allowing the listener to visualize an animated concert scene full of energy from the Nijigasaki girls.": "=Track Listing=="
  },
  "lyrics": {
    "english": "/lyrics/nijigasaki/wawawawhats-up/english.txt",
    "romaji": "/lyrics/nijigasaki/wawawawhats-up/romaji.txt",
    "kanji": "/lyrics/nijigasaki/wawawawhats-up/kanji.txt"
  }
}