{
  "title": "A song for You! You? You!!",
  "group_id": "muse",
  "url": "https://love-live.fandom.com/wiki/A_song_for_You!_You?_You!!",
  "artist": [],
  "album": "",
  "released": "March 25, 2020",
  "composer": [],
  "arranger": [
    "Kyou Takada"
  ],
  "lyricist": [
    "Aki Hata"
  ],
  "center": "Honoka Kosaka",
  "spotify": "",
  "duration": "",
  "categories": [
    "Μ's Songs",
    "Discography",
    "Love Live!",
    "Animated Songs",
    "Lyrics",
    "Single"
  ],
  "description": "A song for You! You? You!! is μ’s first single since 2016. It was released on March 25, 2020.",
  "infobox": {
    "Released": "March 25, 2020",
    "Format": "CD",
    "Recorded": "",
    "Genre": "Anime",
    "Label": "Lantis",
    "Image": "[[File:A_song_for_You_You_You.jpg",
    "Center": "Honoka Kosaka"
  },
  "lyrics": {
    "english": "/lyrics/muse/a-song-for-you-you-you/english.txt",
    "romaji": "/lyrics/muse/a-song-for-you-you-you/romaji.txt",
    "kanji": "/lyrics/muse/a-song-for-you-you-you/kanji.txt"
  }
}