{
  "title": "Junai Lens",
  "group_id": "muse",
  "url": "https://love-live.fandom.com/wiki/Junai_Lens",
  "artist": [],
  "album": "",
  "released": "May 23, 2012",
  "composer": [],
  "arranger": [
    "Yuusuke Yamamoto"
  ],
  "lyricist": [
    "Aki Hata"
  ],
  "center": "",
  "spotify": "https://open.spotify.com/track/0NTXAZn1Jev01NtDN3ur2Z",
  "duration": "",
  "categories": [
    "Lyrics",
    "Discography",
    "Love Live!",
    "Μ's Songs",
    "Solo Songs",
    "Nozomi Tojo"
  ],
  "description": "is a single sung by Nozomi Tojo. The song is also included in μ's Best Album Best Live! Collection.",
  "infobox": {
    "Released": "May 23, 2012",
    "Format": "CD",
    "Recorded": "2012",
    "Label": "Lantis",
    "Image": "[[File:Otome Shiki Ren'ai Juku.jpg"
  },
  "lyrics": {
    "english": "/lyrics/muse/junai-lens/english.txt",
    "romaji": "/lyrics/muse/junai-lens/romaji.txt",
    "kanji": "/lyrics/muse/junai-lens/kanji.txt"
  }
}