{
  "title": "Nightingale Love Song",
  "group_id": "muse",
  "url": "https://love-live.fandom.com/wiki/Nightingale_Love_Song",
  "artist": [],
  "album": "",
  "released": "November 12, 2014",
  "composer": [],
  "arranger": [
    "Kazunori Watanabe"
  ],
  "lyricist": [
    "Aki Hata"
  ],
  "center": "Kotori Minami",
  "spotify": "https://open.spotify.com/track/2yEjuc3iBNB5Ku5LVnGeiD",
  "duration": "",
  "categories": [
    "Love Live!",
    "Discography",
    "Printemps",
    "Lyrics",
    "Μ's Songs",
    "Sub-unit Songs",
    "Honoka Kosaka",
    "Kotori Minami",
    "Hanayo Koizumi"
  ],
  "description": "|lit. Nightingale Love Song}} is a song from Printemps's third single. Printemps is a sub-unit under μ’s; the group consists of Honoka Kosaka, Hanayo Koizumi, and Kotori Minami. It was released on November 12, 2014. It is also included in µ's Best Album Best Live! Collection II.",
  "infobox": {
    "Released": "November 12, 2014",
    "Format": "CD",
    "Recorded": "2014",
    "Label": "Lantis",
    "Image": "[[File:Printemps_Eien_Friends.jpg",
    "Center": "Kotori Minami"
  },
  "lyrics": {
    "english": "/lyrics/muse/nightingale-love-song/english.txt",
    "romaji": "/lyrics/muse/nightingale-love-song/romaji.txt",
    "kanji": "/lyrics/muse/nightingale-love-song/kanji.txt"
  }
}