{
  "title": "Puwa Puwa-O!",
  "group_id": "muse",
  "url": "https://love-live.fandom.com/wiki/Puwa_Puwa-O!",
  "artist": [],
  "album": "",
  "released": "September 25, 2013",
  "composer": [],
  "arranger": [
    "Yuugo Sasakura"
  ],
  "lyricist": [
    "Aki Hata"
  ],
  "center": "Kotori Minami",
  "spotify": "https://open.spotify.com/track/26RTLtH0vbYO7P4RiTSHyq",
  "duration": "3:35",
  "categories": [
    "Discography",
    "Printemps",
    "Lyrics",
    "Love Live!",
    "Μ's Songs",
    "Sub-unit Songs",
    "Honoka Kosaka",
    "Kotori Minami",
    "Hanayo Koizumi"
  ],
  "description": "is a bonus CD by Printemps. Printemps is a sub-unit under μ’s; the group consists of Honoka Kosaka, Hanayo Koizumi, and Kotori Minami. The bonus CD is included in purchasing the entire Love Live! Season 1 Blu-rays from . It was released on September 25, 2013.",
  "infobox": {
    "Released": "September 25, 2013",
    "Center": "Kotori Minami",
    "Format": "CD",
    "Recorded": "2013",
    "Genre": "Anime",
    "Length": "3:35",
    "Label": "Lantis",
    "Image": "[[File:Printemps Puwa Puwa O.jpg"
  },
  "lyrics": {
    "english": "/lyrics/muse/puwa-puwa-o/english.txt",
    "romaji": "/lyrics/muse/puwa-puwa-o/romaji.txt",
    "kanji": "/lyrics/muse/puwa-puwa-o/kanji.txt"
  }
}