{
  "title": "Animelo Summer Live",
  "group_id": "aqours",
  "url": "https://love-live.fandom.com/wiki/Animelo_Summer_Live",
  "artist": [],
  "album": "",
  "released": "",
  "composer": [],
  "arranger": [],
  "lyricist": [],
  "center": "",
  "spotify": "",
  "duration": "",
  "categories": [
    "Live Concerts",
    "Discography",
    "Discography:Aqours",
    "Discography:Nijigaku",
    "Discography:Liella!",
    "Love Live!",
    "Love Live! Sunshine!!",
    "Love Live! Nijigaku",
    "Love Live! Superstar!!"
  ],
  "description": "Animelo Summer Live (Anisama for short) is the biggest anime music festival in the world. Originally held in 2005, it has been held at Saitama Super Arena since 2008 and regularly draws crowds in excess of 80,000 people over multiple days.",
  "infobox": {},
  "lyrics": {
    "english": null,
    "romaji": null,
    "kanji": null
  }
}