{
  "title": "Natsu e no Tobira Never end ver.",
  "group_id": "aqours",
  "url": "https://love-live.fandom.com/wiki/Natsu_e_no_Tobira_Never_end_ver.",
  "artist": [
    "Riko Sakurauchi",
    "Hanamaru Kunikida",
    "Mari Ohara"
  ],
  "album": "",
  "released": "August 2, 2017",
  "composer": [],
  "arranger": [
    "Masashi Kanasaki"
  ],
  "lyricist": [
    "Aki Hata"
  ],
  "center": "Riko Sakurauchi",
  "spotify": "https://open.spotify.com/track/2tkXgl87zjKfDUFkht3maK",
  "duration": "",
  "categories": [
    "Discography:Aqours",
    "Love Live! Sunshine!!",
    "Aqours Songs",
    "Lyrics",
    "Duo Trio Songs:Aqours",
    "Riko Sakurauchi",
    "Hanamaru Kunikida",
    "Mari Ohara",
    "Radio Dramas"
  ],
  "description": "is a song included in Love Live!! Sunshine!! Duo &amp; Trio Collection CD Vol. 1 Summer Vacation which was released on August 2, 2017. It is sung by Riko Sakurauchi, Hanamaru Kunikida, and Mari Ohara.",
  "infobox": {
    "Artist": "Riko Sakurauchi, Hanamaru Kunikida, and Mari Ohara",
    "Released": "August 2, 2017",
    "Format": "CD",
    "Recorded": "2017",
    "Length": "",
    "Label": "Lantis",
    "Image": "[[File:Duo Trio Collection CD Vol 1 Summer Vacation.jpg",
    "Center": "Riko Sakurauchi",
    "Masashi Kanasaki]].": "=SIF 2: Miracle Live Description==",
    "lit. Faraway of the North, Riko, Mari and Hanamaru and……}}": "=Video==",
    "Subbed Radio Dramas": "'''External Link: [https://drive.google.com/drive/folders/111C3PcyZEpMxvzyMhW7BuT0n9ipf0EVy Subbed Duo & Trio Collection CD Vol. 1 Summer Vacation Radio Dramas by xIceArcher]'''"
  },
  "lyrics": {
    "english": "/lyrics/aqours/natsu-e-no-tobira-never-end-ver/english.txt",
    "romaji": "/lyrics/aqours/natsu-e-no-tobira-never-end-ver/romaji.txt",
    "kanji": "/lyrics/aqours/natsu-e-no-tobira-never-end-ver/kanji.txt"
  }
}